{
  "app_type": "marketplace",
  "app_name": "GreenLoop Connect",
  "tagline": "Find certified green suppliers and offset your carbon footprint in one trusted marketplace.",
  "primary_color": "#2E7D32",
  "accent_color": "#81C784",
  "sections": [
    "Hero",
    "Supplier Directory",
    "Carbon Offset Products",
    "Green Certifications",
    "How It Works",
    "Testimonials",
    "Contact Us"
  ],
  "backend_resources": [
    "suppliers",
    "products",
    "certifications",
    "reviews",
    "orders",
    "users"
  ],
  "features": [
    "Advanced search and filters by certification, industry, and location",
    "Supplier profiles with verified sustainability credentials",
    "Integrated carbon offset product catalog"
  ]
}